Metadata-Version: 2.4
Name: claimed
Version: 0.2.3
Summary: The CLAIMED framework
Home-page: https://github.com/claimed-framework/component-library
Author: The CLAIMED authors
Author-email: The CLAIMED authors <claimed-framework@proton.me>
Maintainer: Benedikt Blumenstiel
Maintainer-email: Romeo Kienzler <claimed-framework@proton.me>
License:                                  Apache License
Project-URL: Homepage, https://github.com/claimed-framework/c3
Project-URL: Bug Tracker, https://github.com/claimed-framework/c3/issues
Keywords: CLAIMED,compiler,KubeFlow,Kubernetes
Classifier: Programming Language :: Python :: 3
Classifier: License :: OSI Approved :: Apache Software License
Classifier: Operating System :: OS Independent
Requires-Python: >=3.7
License-File: LICENSE
Requires-Dist: nbconvert>=7.9.2
Requires-Dist: ipython>=8.16.1
Requires-Dist: traitlets>=5.11.2
Requires-Dist: pandas
Requires-Dist: boto3
Dynamic: author
Dynamic: home-page
Dynamic: license-file
